{
    "app_name": "WatchYaari",  //Name of the app
    "description": "Watch videos with your friends", // One line description
    "hidden": "true", // Can be "true" or "false". If true, this app won't show up in Launchpad.
    "rank": "40", // This is used to sort the apps in the launchpad. 1 to 20 are reserved. Enter greater than 20
    "type": "Full App", //Can be "Building Block" or "Full App"
    "contributed_by": "", // Can be "Redis Labs" or "Community" or "Partner"
    "repo_url": "https://github.com/AkhilJSON/watchyaari", //This is the Gitub Repo's URL.
    "download_url": "https://github.com/AkhilJSON/watchyaari/archive/refs/heads/AkhilJSON-readme-changes.zip",//This is a direct link to the Github's download button so people can download it directly from the Marketplace
    "language": ["JavaScript", "NodeJS"], // Backend technologies: "JavaScript", "Java", "Python", "Go", "C#", "Ruby", "PHP", etc. 
    "redis_commands": ["JSON.SET", "JSON.GET", "FT.SEARCH", ""], // Enter all the Redis commands
    "redis_features": ["caching"],// Enter any core Redis feature or leave it blank.
    "redis_modules": ["RediJSON", "RediSearch"], //Value can be one or more of "RediJSON", "", "RedisTimeseries", "RedisAI"  "RedisGears" or "RedisGraph" listed in an array. 
    "app_image_urls": [
        "https://user-images.githubusercontent.com/26838762/186484887-8f5361ba-e309-49bb-af05-f82a28a977e6.png" ,
        "https://user-images.githubusercontent.com/26838762/186484922-de0fcb3c-6f29-4b10-9417-8068ad4d4805.png",
        "https://user-images.githubusercontent.com/26838762/186473611-184617fe-01d8-48cf-b6f2-6c9b2a83ec17.png",
        "https://user-images.githubusercontent.com/26838762/186485907-9caf871b-40ad-4f19-9642-13545d0bb428.png",
        "https://user-images.githubusercontent.com/26838762/186484722-109020aa-fc22-4e4a-8f6e-f0a127599907.png",
        "https://user-images.githubusercontent.com/26838762/186484785-19041544-ca3d-473c-8126-89da5f1f96c7.png",
        "https://user-images.githubusercontent.com/26838762/186486192-0e5bcbce-7c6b-45f9-b115-c02cd0559b80.png",
        "https://user-images.githubusercontent.com/26838762/186486403-ed2edb93-5e0e-48a5-bd37-8d8a7815e12e.png",
        "https://user-images.githubusercontent.com/26838762/187056564-db66a18e-4010-416a-a989-34838c8f337f.png",

    ], // Provide any image urls in an array.
    "youtube_url": "", //Provide a Youtube link to your app's video
    "special_tags": ["Hackathon", "Redis Hackathon on DEV"], // "Hackathon", "Paid", or any event names.
    "verticals": ["Online Watch Party"], // Can be: "Healthcare", "Financial", "Tourism", "Retail", "Oil & Gas", "Manufacturing", "Technology","Education", "Construction"  
    "markdown": "https://raw.githubusercontent.com/AkhilJSON/watchyaari/master/README.md" // Link to the RAW Markdown.
}
